{
  "configVersion": 1,
  "index": "http://drumband-pvsj.be/index.html",
  "assetGroups": [
    {
      "name": "app",
      "installMode": "prefetch",
      "updateMode": "prefetch",
      "urls": [
        "http://drumband-pvsj.be/favicon.ico",
        "http://drumband-pvsj.be/index.html",
        "http://drumband-pvsj.be/inline.9fdf46bde7a9b8510d5b.bundle.js",
        "http://drumband-pvsj.be/main.8ce13460788274baade3.bundle.js",
        "http://drumband-pvsj.be/polyfills.7b28aac51a49ee394f30.bundle.js",
        "http://drumband-pvsj.be/scripts.76d47550469c8c7be4cd.bundle.js",
        "http://drumband-pvsj.be/styles.1b3ed22b1d5b16af8edf.bundle.css"
      ],
      "patterns": []
    },
    {
      "name": "assets",
      "installMode": "lazy",
      "updateMode": "prefetch",
      "urls": [
        "http://drumband-pvsj.be/assets/data/scores.json",
        "http://drumband-pvsj.be/assets/img/burger.png",
        "http://drumband-pvsj.be/assets/img/contact_1.jpg",
        "http://drumband-pvsj.be/assets/img/home_1.jpg",
        "http://drumband-pvsj.be/assets/img/home_1_small.jpg",
        "http://drumband-pvsj.be/assets/img/home_2.jpg",
        "http://drumband-pvsj.be/assets/img/home_3.jpg",
        "http://drumband-pvsj.be/assets/img/image_0.jpg",
        "http://drumband-pvsj.be/assets/img/image_1.jpg",
        "http://drumband-pvsj.be/assets/img/image_2.jpg",
        "http://drumband-pvsj.be/assets/img/image_3.jpg",
        "http://drumband-pvsj.be/assets/img/image_4.jpg",
        "http://drumband-pvsj.be/assets/img/image_5.jpg",
        "http://drumband-pvsj.be/assets/img/image_6.jpg",
        "http://drumband-pvsj.be/assets/img/image_7.jpg",
        "http://drumband-pvsj.be/assets/img/logo.jpg",
        "http://drumband-pvsj.be/assets/img/logo.png"
      ],
      "patterns": []
    }
  ],
  "dataGroups": [],
  "hashTable": {
    "http://drumband-pvsj.be/inline.9fdf46bde7a9b8510d5b.bundle.js": "6808a01a6cfc679eb59e1d09bf712d2914a6c7bd",
    "http://drumband-pvsj.be/assets/data/scores.json": "61afabc35c29bf54836695d8214e2f398125a715",
    "http://drumband-pvsj.be/main.8ce13460788274baade3.bundle.js": "b858b16e1d9b3319cf1f2c9f849ee693e4ad6720",
    "http://drumband-pvsj.be/assets/img/burger.png": "74c64dac8dc4a4323e88edf9c3ec20e3e68bfe8b",
    "http://drumband-pvsj.be/polyfills.7b28aac51a49ee394f30.bundle.js": "c7b365ef47db91a7d672881b233f740827cbc545",
    "http://drumband-pvsj.be/assets/img/contact_1.jpg": "1abbcd0512a1ad49bb74b26b3698ef6de207645a",
    "http://drumband-pvsj.be/scripts.76d47550469c8c7be4cd.bundle.js": "447527590928fb8f51cbc0b26270051e94c8aaf2",
    "http://drumband-pvsj.be/assets/img/home_1.jpg": "6dc64a0bc5552c128bdc135056154f33d9eb9add",
    "http://drumband-pvsj.be/styles.1b3ed22b1d5b16af8edf.bundle.css": "489415c02cdfb68a104c54d45fed76c5558fb2e8",
    "http://drumband-pvsj.be/assets/img/home_1_small.jpg": "2b18f7e49fd2bb54180c9d2d84c11e00297c4552",
    "http://drumband-pvsj.be/favicon.ico": "84161b857f5c547e3699ddfbffc6d8d737542e01",
    "http://drumband-pvsj.be/assets/img/home_2.jpg": "c76f245ce467fbfc778a02f8e370ebe25859ff38",
    "http://drumband-pvsj.be/index.html": "0c0963a7f15e2f18bf8004965a3f544d497f01a3",
    "http://drumband-pvsj.be/assets/img/home_3.jpg": "d6865f07d3bf4205d5c0d01c0d154fc9043cf192",
    "http://drumband-pvsj.be/assets/img/image_0.jpg": "61b08d528bbd72410d951ec6799610f24feb25a6",
    "http://drumband-pvsj.be/assets/img/image_1.jpg": "d1009ffa82e2b18d3fb9314e87b91e7b82fada50",
    "http://drumband-pvsj.be/assets/img/image_2.jpg": "8741f564f42114fbe303183c656fdfdae8d382d4",
    "http://drumband-pvsj.be/assets/img/image_3.jpg": "3a99dbf5508b227bca1bc8cfc68d23eb8c2e23b5",
    "http://drumband-pvsj.be/assets/img/image_4.jpg": "c86a61d3f5b1f2708c0fc387a8500f4911abd9ce",
    "http://drumband-pvsj.be/assets/img/image_5.jpg": "80bd898a2e10d0530b95cc39cb8e4977981a5f7f",
    "http://drumband-pvsj.be/assets/img/image_6.jpg": "b85feb83da6dd8c192d399eb45c5ca1c9fb1664b",
    "http://drumband-pvsj.be/assets/img/image_7.jpg": "4796d22614db30b52e9cacebadf15e9b7f3b0cce",
    "http://drumband-pvsj.be/assets/img/logo.jpg": "296fb13966b3a369d56174babd339a0371380139",
    "http://drumband-pvsj.be/assets/img/logo.png": "b5011417cd2bc6323ab0b37d10641fbc4abbece8"
  }
}